{
    "DefaultSetting": {
        "time": 300,
        "optimal": false,
        "obj": 220,
        "sol": [
            [
                4
            ],
            [
                1,
                2
            ],
            [
                10,
                9
            ],
            [
                3
            ],
            [
                7
            ],
            [],
            [
                6,
                5
            ],
            [
                8
            ]
        ]
    },
    "Feasibility": {
        "time": 300,
        "optimal": false,
        "obj": 220,
        "sol": [
            [
                4
            ],
            [
                1,
                2
            ],
            [
                10,
                9
            ],
            [
                3
            ],
            [
                7
            ],
            [],
            [
                6,
                5
            ],
            [
                8
            ]
        ]
    },
    "Optimality": {
        "time": 300,
        "optimal": false,
        "obj": 220,
        "sol": [
            [
                4
            ],
            [
                1,
                2
            ],
            [
                10,
                9
            ],
            [
                3
            ],
            [
                7
            ],
            [],
            [
                6,
                5
            ],
            [
                8
            ]
        ]
    },
    "Gurobi_Default": {
        "time": 300,
        "optimal": false,
        "obj": 220,
        "sol": [
            [],
            [
                10,
                8
            ],
            [
                3
            ],
            [
                4
            ],
            [
                1
            ],
            [
                2
            ],
            [
                7
            ],
            [
                9,
                5,
                6
            ]
        ]
    },
    "Gurobi_Feasibility": {
        "time": 239,
        "optimal": true,
        "obj": 220,
        "sol": [
            [
                6
            ],
            [
                10,
                7
            ],
            [
                8
            ],
            [
                2,
                9,
                5,
                3
            ],
            [
                4
            ],
            [
                1
            ],
            [],
            []
        ]
    },
    "Gurobi_Optimality": {
        "time": 79,
        "optimal": true,
        "obj": 220,
        "sol": [
            [
                10,
                8
            ],
            [
                7,
                4
            ],
            [],
            [],
            [
                3,
                6
            ],
            [
                9
            ],
            [
                2,
                5,
                1
            ],
            []
        ]
    }
}
